traffic_anonymous/__init__.py
traffic_anonymous/cli/__init__.py
traffic_anonymous/cli/main.py
traffic_anonymous/crypo/__init__.py
traffic_anonymous/crypo/decrypt.py
traffic_anonymous/crypo/encrypt.py
traffic_anonymous/myutils/__init__.py
traffic_anonymous/myutils/config.py
traffic_anonymous/myutils/logger.py
traffic_anonymous/myutils/utils.py
traffic_anonymous-1.0.1.data/data/requirements.txt
traffic_anonymous-1.0.1.dist-info/METADATA
traffic_anonymous-1.0.1.dist-info/WHEEL
traffic_anonymous-1.0.1.dist-info/entry_points.txt
traffic_anonymous-1.0.1.dist-info/top_level.txt
traffic_anonymous-1.0.1.dist-info/RECORD
