Metadata-Version: 2.1
Name: traffic-anonymous
Version: 1.0.1
Summary: 流量匿名化工具
Home-page: https://pypi.org/project/traffic_anonymous
Author: aimafan
Author-email: chongrufan@nuaa.edu.cn
Classifier: Programming Language :: Python :: 3
Classifier: License :: OSI Approved :: MIT License
Classifier: Operating System :: OS Independent
Requires-Python: >=3.6
Requires-Dist: certifi ==2024.2.2
Requires-Dist: cffi ==1.16.0
Requires-Dist: charset-normalizer ==3.3.2
Requires-Dist: click ==8.1.7
Requires-Dist: crypto ==1.4.1
Requires-Dist: cryptography ==42.0.5
Requires-Dist: idna ==3.7
Requires-Dist: Naked ==0.1.32
Requires-Dist: pycparser ==2.22
Requires-Dist: PyYAML ==6.0.1
Requires-Dist: requests ==2.31.0
Requires-Dist: shellescape ==3.8.1
Requires-Dist: tqdm ==4.66.2
Requires-Dist: urllib3 ==2.2.1
